chainlearn/__init__.py
chainlearn/utils.py
chainlearn-0.0.2.dev0.dist-info/DESCRIPTION.rst
chainlearn-0.0.2.dev0.dist-info/METADATA
chainlearn-0.0.2.dev0.dist-info/RECORD
chainlearn-0.0.2.dev0.dist-info/WHEEL
chainlearn-0.0.2.dev0.dist-info/metadata.json
chainlearn-0.0.2.dev0.dist-info/top_level.txt
