Metadata-Version: 2.0
Name: chainlearn
Version: 0.0.2.dev0
Summary: chainlearn: A sprinkle of syntax sugar for pandas/sklearn
Home-page: https://github.com/dimenwarper/chainlearn/
Author: Pablo Cordero
Author-email: dimenwarper@gmail.com
Maintainer: Pablo Cordero
Maintainer-email: dimenwarper@gmail.com
License: BSD (3-clause)
Download-URL: https://github.com/dimenwarper/chainlearn/
Platform: UNKNOWN
Requires-Dist: pandas (>=0.15.2)
Requires-Dist: scikit-learn (>=0.19.0)
